mlx/__main__.py
mlx/_os_warning.py
mlx/_reprlib_fix.py
mlx/core.cpython-39-darwin.so
mlx/distributed_run.py
mlx/extension.py
mlx/mlx.pyi
mlx/py.typed
mlx/utils.py
mlx/core/__init__.pyi
mlx/core/distributed/__init__.pyi
mlx/core/fast/__init__.pyi
mlx/core/fft/__init__.pyi
mlx/core/linalg/__init__.pyi
mlx/core/metal/__init__.pyi
mlx/core/random/__init__.pyi
mlx/nn/__init__.py
mlx/nn/init.py
mlx/nn/losses.py
mlx/nn/utils.py
mlx/nn/layers/__init__.py
mlx/nn/layers/activations.py
mlx/nn/layers/base.py
mlx/nn/layers/containers.py
mlx/nn/layers/convolution.py
mlx/nn/layers/convolution_transpose.py
mlx/nn/layers/distributed.py
mlx/nn/layers/dropout.py
mlx/nn/layers/embedding.py
mlx/nn/layers/linear.py
mlx/nn/layers/normalization.py
mlx/nn/layers/pooling.py
mlx/nn/layers/positional_encoding.py
mlx/nn/layers/quantized.py
mlx/nn/layers/recurrent.py
mlx/nn/layers/transformer.py
mlx/nn/layers/upsample.py
mlx/optimizers/__init__.py
mlx/optimizers/optimizers.py
mlx/optimizers/schedulers.py
mlx_awni_test-0.26.5.dist-info/licenses/LICENSE
mlx_awni_test-0.26.5.dist-info/METADATA
mlx_awni_test-0.26.5.dist-info/WHEEL
mlx_awni_test-0.26.5.dist-info/entry_points.txt
mlx_awni_test-0.26.5.dist-info/top_level.txt
mlx_awni_test-0.26.5.dist-info/RECORD
