Metadata-Version: 2.4
Name: mlx-awni-test
Version: 0.26.5
Summary: A framework for machine learning on Apple silicon.
Home-page: https://github.com/ml-explore/mlx
Author: MLX Contributors
Author-email: mlx@group.apple.com
License: MIT
Requires-Python: >=3.9
License-File: LICENSE
Requires-Dist: mlx-metal-awni-test==0.26.5; platform_system == "Darwin"
Provides-Extra: dev
Requires-Dist: nanobind==2.4.0; extra == "dev"
Requires-Dist: numpy; extra == "dev"
Requires-Dist: pre-commit; extra == "dev"
Requires-Dist: setuptools>=80; extra == "dev"
Requires-Dist: torch; extra == "dev"
Requires-Dist: typing_extensions; extra == "dev"
Provides-Extra: cuda
Requires-Dist: mlx-cuda-awni-test==0.26.5; platform_system == "Linux" and extra == "cuda"
Provides-Extra: cpu
Requires-Dist: mlx-cpu-awni-test==0.26.5; platform_system == "Linux" and extra == "cpu"
Dynamic: author
Dynamic: author-email
Dynamic: description
Dynamic: description-content-type
Dynamic: home-page
Dynamic: license
Dynamic: license-file
Dynamic: provides-extra
Dynamic: requires-dist
Dynamic: requires-python
Dynamic: summary
